daily_art/__init__.py
daily_art/main.py
say_hello/__init__.py
say_hello/main.py
dailyArt-0.0.1.dist-info/LICENSE
dailyArt-0.0.1.dist-info/METADATA
dailyArt-0.0.1.dist-info/WHEEL
dailyArt-0.0.1.dist-info/top_level.txt
dailyArt-0.0.1.dist-info/RECORD
